falsedto/__init__.py
falsedto/hough.cpython-37m-x86_64-linux-gnu.so
falsedto/hough.py
falsedto/misc.py
falsedto/tests/__init__.py
falsedto/tests/fitting.py
falsedto/tests/score_box.py
falsedto/tests/score_map.py
falsedto-0.5.0.dist-info/LICENSE
falsedto-0.5.0.dist-info/METADATA
falsedto-0.5.0.dist-info/WHEEL
falsedto-0.5.0.dist-info/top_level.txt
falsedto-0.5.0.dist-info/RECORD
