Metadata-Version: 2.1
Name: falsedto
Version: 0.5.0
Summary: falsedto: Faint Line Segment Detection Tool
Home-page: https://bitbucket.org/ryou_ohsawa/falsedt/src/master/
Author: Ryou Ohsawa
Author-email: ohsawa@ioa.s.u-tokyo.ac.jp
Maintainer: Ryou Ohsawa
Maintainer-email: ohsawa@ioa.s.u-tokyo.ac.jp
License: MIT
Platform: UNKNOWN
Classifier: Development Status :: 3 - Alpha
Classifier: Environment :: Console
Classifier: Intended Audience :: Science/Research
Classifier: License :: OSI Approved :: MIT License
Classifier: Operating System :: POSIX :: Linux
Classifier: Programming Language :: Python :: 3
Classifier: Programming Language :: Python :: 3.7
Classifier: Topic :: Scientific/Engineering :: Astronomy
Requires-Dist: numpy
Requires-Dist: matplotlib
Requires-Dist: sep
